Consoldation_utility/Consolidation.py
Consoldation_utility/__init__.py
Pandas_Consolidated_Loader-0.2.dist-info/METADATA
Pandas_Consolidated_Loader-0.2.dist-info/WHEEL
Pandas_Consolidated_Loader-0.2.dist-info/top_level.txt
Pandas_Consolidated_Loader-0.2.dist-info/RECORD
