Metadata-Version: 2.1
Name: Pandas-Consolidated-Loader
Version: 0.2
Requires-Dist: pandas
Requires-Dist: xlsxwriter
Requires-Dist: openpyxl
Requires-Dist: configparser
